MANIFEST.in
README.md
setup.py
pysdl2_sdl2ui.egg-info/PKG-INFO
pysdl2_sdl2ui.egg-info/SOURCES.txt
pysdl2_sdl2ui.egg-info/dependency_links.txt
pysdl2_sdl2ui.egg-info/not-zip-safe
pysdl2_sdl2ui.egg-info/requires.txt
pysdl2_sdl2ui.egg-info/top_level.txt
sdl2ui/__init__.py
sdl2ui/app.py
sdl2ui/audio.py
sdl2ui/debugger.py
sdl2ui/joystick.py
sdl2ui/mixer.py
sdl2ui/mixins.py
sdl2ui/resource.py
sdl2ui/data/font-6.png