Metadata-Version: 1.1
Name: pysdl2-sdl2ui
Version: 0.1.14
Summary: A Python library to make simple UI using pysdl2
Home-page: https://github.com/cecton/pysdl2-sdl2ui
Author: Cecile Tonglet
Author-email: cecile.tonglet@gmail.com
License: MIT
Platform: UNKNOWN
Classifier: Development Status :: 1 - Planning
Classifier: Intended Audience :: Developers
Classifier: Natural Language :: English
Classifier: License :: OSI Approved :: MIT License
Classifier: Programming Language :: Python
Classifier: Programming Language :: Python :: 2.7
Classifier: Programming Language :: Python :: 3
Classifier: Programming Language :: Python :: 3.3
Classifier: Programming Language :: Python :: 3.4
Classifier: Programming Language :: Python :: 3.5
